smart_financial_mcp/__init__.py
smart_financial_mcp/server.py
smart_financial_mcp-1.0.0.dist-info/METADATA
smart_financial_mcp-1.0.0.dist-info/WHEEL
smart_financial_mcp-1.0.0.dist-info/entry_points.txt
smart_financial_mcp-1.0.0.dist-info/licenses/LICENSE
smart_financial_mcp-1.0.0.dist-info/RECORD
